psycopg2_helper/__init__.py
psycopg2_helper/bp/__init__.py
psycopg2_helper/bp/postgres_helper.py
psycopg2_helper/dmo/__init__.py
psycopg2_helper/dmo/postgres_connector.py
psycopg2_helper/svc/__init__.py
psycopg2_helper/svc/perform_runtime_crud.py
psycopg2_helper/svc/perform_table_operations.py
psycopg2_helper-0.1.5.dist-info/WHEEL
psycopg2_helper-0.1.5.dist-info/METADATA
psycopg2_helper-0.1.5.dist-info/RECORD
