Metadata-Version: 2.1
Name: psycopg2-helper
Version: 0.1.5
Summary: Helper Functions for Postgres
Home-page: https://github.com/craigtrim/psycopg2-helper
License: MIT
Keywords: postgres,db,rdb,rdbms,helper,utility,psycopg2
Author: Craig Trim
Author-email: craigtrim@gmail.com
Maintainer: Craig Trim
Maintainer-email: craigtrim@gmail.com
Requires-Python: >=3.8.5,<4.0.0
Classifier: Development Status :: 4 - Beta
Classifier: License :: OSI Approved :: MIT License
Classifier: Programming Language :: Python :: 3
Classifier: Programming Language :: Python :: 3.10
Classifier: Programming Language :: Python :: 3.9
Classifier: Topic :: Software Development :: Libraries :: Python Modules
Requires-Dist: baseblock
Requires-Dist: psycopg2
Project-URL: Bug Tracker, https://github.com/craigtrim/psycopg2-helper/issues
Project-URL: Repository, https://github.com/craigtrim/psycopg2-helper
